{
  "airdate": 942210000,
  "scenes": [
    {
      "dialogue": [
        {
          "character": "JISA",
          "line": "Gedrin! Gedrin! What happened? I lost you."
        },
        {
          "character": "GEDRIN",
          "line": "Thirty seven bio-pods were damaged. I had to diskonnect them from the reactor."
        },
        {
          "character": "JISA",
          "line": "Were they dead?"
        },
        {
          "character": "GEDRIN",
          "line": "I had no choice. The main power's holding. The rest of the bio-pods are secure. That leaves us. Don't look so worried. It'll be like a simple night's sleep. We're out of time."
        },
        {
          "character": "JISA",
          "line": "Do you think we'll dream?"
        },
        {
          "character": "GEDRIN",
          "line": "I don't know. We'll get through this."
        },
        {
          "character": "JISA",
          "line": "What if there's nothing left?"
        },
        {
          "character": "GEDRIN",
          "line": "We'll start again. Five years."
        }
      ],
      "location": "Vaadwaur cave -\nstasis chamber"
    },
    {
      "dialogue": [
        {
          "character": "JANEWAY",
          "line": "Report."
        },
        {
          "character": "KIM",
          "line": "We've entered some kind of a subspace corridor."
        },
        {
          "character": "PARIS",
          "line": "We were cruising at warp six then, wham, this thing pulled at our warp field like a magnet."
        },
        {
          "character": "JANEWAY",
          "line": "Where did that debris come from?"
        },
        {
          "character": "TUVOK",
          "line": "Unknown, but the corridor is filled with it. Metal fragments, plasma exhaust, organic residue."
        },
        {
          "character": "SEVEN",
          "line": "Some of the debris is over eight hundred years old, Captain."
        },
        {
          "character": "JANEWAY",
          "line": "I'd like to avoid becoming part of this garbage stream. Can you find a way out?"
        },
        {
          "character": "PARIS",
          "line": "I don't now. There's hundreds of corridors. It's like a maze."
        },
        {
          "character": "JANEWAY",
          "line": "Well, be a good rat and find us the cheese, hmm?"
        },
        {
          "character": "PARIS",
          "line": "I'll do my best, Captain."
        },
        {
          "character": "CHAKOTAY",
          "line": "Tuvok?"
        },
        {
          "character": "TUVOK",
          "line": "It was a vessel, sir. They are hailing us."
        },
        {
          "character": "JANEWAY",
          "line": "Put it through."
        },
        {
          "character": "TUREI",
          "line": "Who are you?",
          "modifier": "screen"
        },
        {
          "character": "JANEWAY",
          "line": "I'm Captain Kathryn Janeway of the Starship Voyager. And you are?"
        },
        {
          "character": "TUREI",
          "line": "This underspace belongs to us.",
          "modifier": "screen"
        },
        {
          "character": "JANEWAY",
          "line": "We're here by accident. We're trying to find a way out. Can you help us?"
        },
        {
          "character": "TUREI",
          "line": "Help you? Yes, we'll help you.",
          "modifier": "screen"
        },
        {
          "character": "TUVOK",
          "line": "They are targeting our shields with a resonance pulse. It's altering the harmonics. We're being pushed out of the corridor."
        },
        {
          "character": "PARIS",
          "line": "We're clear."
        },
        {
          "character": "TUVOK",
          "line": "The vessel has exited the corridor as well."
        },
        {
          "character": "PARIS",
          "line": "Captain, we're over two hundred light years from where we entered the corridor."
        },
        {
          "character": "KIM",
          "line": "Two hundred light years in five minutes?"
        },
        {
          "character": "JANEWAY",
          "line": "Hail them. Thank you for your help. There's something I'd like to ask you. We've got a long journey ahead of us and I was wondering if we could negotiate passage through this underspace of yours."
        },
        {
          "character": "TUREI",
          "line": "Lower your shields. Prepare to be boarded.",
          "modifier": "screen"
        },
        {
          "character": "CHAKOTAY",
          "line": "Boarded? For what reason?"
        },
        {
          "character": "TUREI",
          "line": "We must purge your computer. Remove all readings you've gathered in our territory.",
          "modifier": "screen"
        },
        {
          "character": "JANEWAY",
          "line": "We pose no threat to you. We're simply trying"
        },
        {
          "character": "TUREI",
          "line": "We're going to destroy that information, one way or another. Lower your shields.",
          "modifier": "screen"
        },
        {
          "character": "JANEWAY",
          "line": "I won't do that."
        },
        {
          "character": "JANEWAY",
          "line": "Evasive maneuvers. Try to disable them."
        },
        {
          "character": "TUVOK",
          "line": "Their vessel is highly maneuverable. It's difficult to get a phaser lock."
        },
        {
          "character": "KIM",
          "line": "Picking up two more ships heading our way ."
        },
        {
          "character": "PARIS",
          "line": "Direct hit. Our warp drive is offline."
        },
        {
          "character": "TUVOK",
          "line": "Shields down to eighty two percent. Sixty percent."
        },
        {
          "character": "PARIS",
          "line": "They're closing."
        },
        {
          "character": "CHAKOTAY",
          "line": "We could use some clever suggestions about now."
        },
        {
          "character": "SEVEN",
          "line": "There's a planet eight million kilometers ahead, uninhabited. But the atmosphere is charged with radiogenic particles."
        },
        {
          "character": "CHAKOTAY",
          "line": "How radiogenic?"
        },
        {
          "character": "SEVEN",
          "line": "Three thousand isorems."
        },
        {
          "character": "CHAKOTAY",
          "line": "If we route enough power to the shields we can survive in that, but maybe our friends can't."
        },
        {
          "character": "TUVOK",
          "line": "Shields at fifty three percent."
        },
        {
          "character": "JANEWAY",
          "line": "Do it."
        },
        {
          "character": "PARIS",
          "line": "Entering the thermosphere."
        },
        {
          "character": "KIM",
          "line": "Radiation levels at three thousand isorems and climbing."
        },
        {
          "character": "CHAKOTAY",
          "line": "The alien ships?"
        },
        {
          "character": "TUVOK",
          "line": "In pursuit and charging weapons."
        },
        {
          "character": "JANEWAY",
          "line": "Increase our descent vector."
        },
        {
          "character": "PARIS",
          "line": "They're still closing."
        },
        {
          "character": "TUVOK",
          "line": "Direct hit to our aft shields."
        },
        {
          "character": "JANEWAY",
          "line": "Find the highest concentration of radiation, and take us through it."
        },
        {
          "character": "KIM",
          "line": "Proximity radiation at four thousand isorems. Five thousand. Six."
        },
        {
          "character": "TUVOK",
          "line": "Their shields are weakening. They're breaking off."
        },
        {
          "character": "JANEWAY",
          "line": "Now, all we need is a place to set down and make repairs. Tom?"
        },
        {
          "character": "PARIS",
          "line": "We're clearing the lower stratosphere."
        },
        {
          "character": "JANEWAY",
          "line": "On screen."
        },
        {
          "character": "CHAKOTAY",
          "line": "I thought you said this planet was uninhabited."
        },
        {
          "character": "KIM",
          "line": "Radiation must have interfered with my scans."
        },
        {
          "character": "PARIS",
          "line": "I doubt it's inhabited anymore. Looks like this planet's in the middle of a nuclear winter."
        },
        {
          "character": "TUVOK",
          "line": "Agreed. Gamma radiation levels are highly toxic. The impact crater suggests an orbital bombardment."
        },
        {
          "character": "JANEWAY",
          "line": "How long ago?"
        },
        {
          "character": "KIM",
          "line": "From the rate of radiogenic decay, eight hundred ninety two years."
        },
        {
          "character": "JANEWAY",
          "line": "This must have been a city of millions. Set us down."
        },
        {
          "character": "PARIS",
          "line": "Disengaging engines."
        },
        {
          "character": "JANEWAY",
          "line": "Stand down red alert. Assign damage repair teams, And Tom, make sure B'Elanna has enough help in Engineering. I want those warp engines back online."
        },
        {
          "character": "PARIS",
          "line": "Yes, ma'am."
        },
        {
          "character": "TUVOK",
          "line": "Our friends are still in orbit."
        },
        {
          "character": "CHAKOTAY",
          "line": "Circling like vultures."
        },
        {
          "character": "JANEWAY",
          "line": "Well, they're going to go hungry."
        },
        {
          "character": "CHAKOTAY",
          "line": "Not if they find a way to adapt their shields and come down after us."
        },
        {
          "character": "KIM",
          "line": "Captain, I'm detecting faint life signs coming from a chamber several hundred meters beneath the surface."
        },
        {
          "character": "JANEWAY",
          "line": "Survivors?"
        },
        {
          "character": "CHAKOTAY",
          "line": "After nine hundred years?"
        },
        {
          "character": "JANEWAY",
          "line": "Oversee the repair teams."
        },
        {
          "character": "CHAKOTAY",
          "line": "You're going down there?"
        },
        {
          "character": "JANEWAY",
          "line": "If somebody survived this catastrophe they might need our help. Get a good fix on those coordinates. I don't want to beam into solid rock. Seven, Tuvok, You're with me."
        }
      ],
      "location": "Bridge"
    },
    {
      "dialogue": [
        {
          "character": "JANEWAY",
          "line": "These walls have been reinforced with tritonium. They built this place to last."
        },
        {
          "character": "TUVOK",
          "line": "Most of the power relays are still active."
        },
        {
          "character": "JANEWAY",
          "line": "Not bad after nine centuries."
        },
        {
          "character": "SEVEN",
          "line": "The main reactor is drawing energy from the planet's geothermal core. Efficient."
        },
        {
          "character": "TUVOK",
          "line": "Some kind of stasis pod."
        },
        {
          "character": "SEVEN",
          "line": "This display indicates that there are more chambers behind these walls. Some of them have failed."
        },
        {
          "character": "JANEWAY",
          "line": "It's amazing they survived at all. Let's see what else we can find."
        },
        {
          "character": "JANEWAY",
          "line": "Seven, what are you doing?"
        },
        {
          "character": "SEVEN",
          "line": "I've activated the reanimation sequence. He may be able to provide us with answers."
        },
        {
          "character": "TUVOK",
          "line": "We don't know anything about this species. They could be hostile."
        },
        {
          "character": "SEVEN",
          "line": "Most humanoid cultures are."
        },
        {
          "character": "JANEWAY",
          "line": "Remind me to reacquaint you with away mission protocols."
        },
        {
          "character": "GEDRIN",
          "line": "Who"
        },
        {
          "character": "JANEWAY",
          "line": "It's all right. We're not your enemy. We're from a starship. We diskovered this chamber and revived you."
        },
        {
          "character": "GEDRIN",
          "line": "How long was I"
        },
        {
          "character": "JANEWAY",
          "line": "In stasis? Close to nine hundred years."
        },
        {
          "character": "GEDRIN",
          "line": "Nine hundred? Jisa. Help her, please."
        },
        {
          "character": "GEDRIN",
          "line": "No, Jisa. She was my wife."
        }
      ],
      "location": "Vaadwaur cave - stasis chamber"
    },
    {
      "dialogue": [
        {
          "character": "EMH",
          "line": "I won't hurt you."
        },
        {
          "character": "GEDRIN",
          "line": "I was drifting in and out of consciousness when they brought me here, but I thought I saw you appear out of thin air."
        },
        {
          "character": "EMH",
          "line": "I'm a computer program. A hologram."
        },
        {
          "character": "GEDRIN",
          "line": "And the others?"
        },
        {
          "character": "EMH",
          "line": "Flesh and blood, like yourself."
        },
        {
          "character": "GEDRIN",
          "line": "You're the ones that took me out of stasis. I don't recognize your species."
        },
        {
          "character": "JANEWAY",
          "line": "Human. Our home planet is halfway across the galaxy."
        },
        {
          "character": "GEDRIN",
          "line": "And you've expanded your territory into this space?"
        },
        {
          "character": "JANEWAY",
          "line": "Our ship was brought here by accident. We're trying to get home."
        },
        {
          "character": "GEDRIN",
          "line": "You're Borg."
        },
        {
          "character": "SEVEN",
          "line": "How do you know that?"
        },
        {
          "character": "GEDRIN",
          "line": "Don't you recognize my people? The Vaadwaur?"
        },
        {
          "character": "SEVEN",
          "line": "The Collective's memory from nine hundred years ago is fragmentary."
        },
        {
          "character": "GEDRIN",
          "line": "I've had many encounters with your kind."
        },
        {
          "character": "EMH",
          "line": "And lived to tell about them? Impressive."
        },
        {
          "character": "GEDRIN",
          "line": "How did you find us?"
        },
        {
          "character": "JANEWAY",
          "line": "We needed someplace to hide from the Turei after they found us in one of their subspace corridors."
        },
        {
          "character": "GEDRIN",
          "line": "Their corridors?"
        },
        {
          "character": "JANEWAY",
          "line": "So they claimed."
        },
        {
          "character": "GEDRIN",
          "line": "The corridors were ours. It took centuries to map them. We were the envy of a hundred species, including the Turei."
        },
        {
          "character": "JANEWAY",
          "line": "Are they responsible for what happened to your planet?"
        },
        {
          "character": "GEDRIN",
          "line": "The Turei, and a dozen others. What one couldn't accomplish the others finally did. I would like to look at what's left of my world."
        }
      ],
      "location": "Sickbay"
    },
    {
      "dialogue": [
        {
          "character": "GEDRIN",
          "line": "We made our final stand there."
        },
        {
          "character": "JANEWAY",
          "line": "I've scanned the cavern. You've got a thousand more stasis pods down there, most of them still active. Hundreds of ships, land vehicles, weapons."
        },
        {
          "character": "GEDRIN",
          "line": "A single battalion, and their families. We had planned to come out of stasis after five years. We believed that by then, the Alliance would have been at each other's throats."
        },
        {
          "character": "JANEWAY",
          "line": "You were going to rebuild?"
        },
        {
          "character": "GEDRIN",
          "line": "No, not here. We knew this planet would be poisoned for centuries. We were planning to go to another world, start a colony, hope to find new allies, learn from them."
        },
        {
          "character": "JANEWAY",
          "line": "Your power core is still functioning. It was the controls that were damaged in the attack. That's why you never came out of stasis."
        },
        {
          "character": "GEDRIN",
          "line": "Jisa and I lived there in the old quarter. We had a garden overlooking the street below. It's a shame she didn't show more courage at the end."
        },
        {
          "character": "JANEWAY",
          "line": "Given the circumstances"
        },
        {
          "character": "GEDRIN",
          "line": "That's no excuse."
        },
        {
          "character": "JANEWAY",
          "line": "Pardon me for saying this, but that seems a bit heartless."
        },
        {
          "character": "GEDRIN",
          "line": "When it rains, do you run from doorway to doorway trying to stay dry, getting wet all the while. Or do you just accept the fact that it's raining, and walk with dignity?"
        },
        {
          "character": "JANEWAY",
          "line": "Rain's one thing. Plasma bombs are something else."
        },
        {
          "character": "GEDRIN",
          "line": "But the principle is the same."
        },
        {
          "character": "JANEWAY",
          "line": "I'd bring an umbrella."
        },
        {
          "character": "GEDRIN",
          "line": "Maybe it's not too late to meet a new ally and learn from her."
        },
        {
          "character": "NEELIX",
          "line": "I took the liberty of preparing a large assortment of Delta Quadrant dishes. Hopefully, there's something here that you'll like."
        },
        {
          "character": "GEDRIN",
          "line": "You're Talax-ilzay."
        },
        {
          "character": "NEELIX",
          "line": "Talaxian, but you're right. My ancestors referred to themselves as Talax-ilzay in the old tongue."
        },
        {
          "character": "GEDRIN",
          "line": "The old tongue was new when I met your race."
        },
        {
          "character": "JANEWAY",
          "line": "You traveled all the way to Talaxia?"
        },
        {
          "character": "GEDRIN",
          "line": "And farther. Our corridors took us to many worlds. I'm curious. Have you heard of us, the Vaadwaur?"
        },
        {
          "character": "NEELIX",
          "line": "Oh, I'm afraid there aren't many records from that period, but vaadwaur is a word in the old tongue. It means foolish. I'm sure that it's just a coincidence, of course. I didn't mean to be rude."
        },
        {
          "character": "GEDRIN",
          "line": "Your ancestors were wise. Only fools would let this happen to them."
        },
        {
          "character": "CHAKOTAY",
          "line": "Chakotay to Captain Janeway.",
          "modifier": "voiceover"
        },
        {
          "character": "JANEWAY",
          "line": "Go ahead."
        },
        {
          "character": "CHAKOTAY",
          "line": "Looks like our friends in orbit have found us.",
          "modifier": "voiceover"
        },
        {
          "character": "JANEWAY",
          "line": "We're on our way."
        }
      ],
      "location": "Mess hall"
    },
    {
      "dialogue": [
        {
          "character": "JANEWAY",
          "line": "Report."
        },
        {
          "character": "CHAKOTAY",
          "line": "Six Turei vessels are in orbit, all firing plasma charges."
        },
        {
          "character": "TUVOK",
          "line": "That was two thousand meters to starboard."
        },
        {
          "character": "KIM",
          "line": "Looks like they can't get an exact fix on our position. The radiogenic atmosphere must be disrupting their targeting."
        },
        {
          "character": "TUVOK",
          "line": "Nine hundred meters."
        },
        {
          "character": "PARIS",
          "line": "They're getting closer."
        },
        {
          "character": "CHAKOTAY",
          "line": "We have the same problem. Our torpedoes won't lock on."
        },
        {
          "character": "TUVOK",
          "line": "Direct hit. Aft shields down to eighteen percent."
        },
        {
          "character": "GEDRIN",
          "line": "Captain? Can you transmit a signal through this atmosphere?"
        },
        {
          "character": "JANEWAY",
          "line": "We've already tried talking to them."
        },
        {
          "character": "GEDRIN",
          "line": "I have no intention of speaking with the Turei. We put a sentry satellite in orbit directly above the city. You could use its sensors to help guide your torpedoes."
        },
        {
          "character": "TUVOK",
          "line": "It's there. Intact and functional."
        },
        {
          "character": "GEDRIN",
          "line": "Open a channel. I'll give you the activation code."
        },
        {
          "character": "GEDRIN",
          "line": "I'm a few centuries out of date."
        },
        {
          "character": "KIM",
          "line": "You can enter the activation code here. It's processing our telemetry."
        },
        {
          "character": "JANEWAY",
          "line": "Triangulate. Fire."
        },
        {
          "character": "TUVOK",
          "line": "Direct hit. The lead ship has lost shields. Its propulsion is down."
        },
        {
          "character": "GEDRIN",
          "line": "One more torpedo will finish them."
        },
        {
          "character": "CHAKOTAY",
          "line": "The other ships are retreating."
        },
        {
          "character": "GEDRIN",
          "line": "Captain, why don't you keep firing?"
        },
        {
          "character": "JANEWAY",
          "line": "We scared them off. That's enough for now."
        },
        {
          "character": "GEDRIN",
          "line": "But they'll come back with twice as many ships."
        },
        {
          "character": "JANEWAY",
          "line": "With any luck, our warp drive will be back online by then."
        },
        {
          "character": "GEDRIN",
          "line": "The Turei may be cowards, but their technology has become much more advanced than ours. If you leave us, we will be slaughtered again."
        },
        {
          "character": "CHAKOTAY",
          "line": "What do you propose?"
        },
        {
          "character": "GEDRIN",
          "line": "Help us off this planet, and we will show you subspace corridors known to nobody else. You will be free from the Turei, and you will be a thousand light years closer to your home."
        },
        {
          "character": "JANEWAY",
          "line": "Let's wake up your battalion."
        }
      ],
      "location": "Bridge"
    },
    {
      "dialogue": [
        {
          "character": "CHAKOTAY",
          "line": "Dragon's teeth."
        },
        {
          "character": "JANEWAY",
          "line": "Dragon's teeth?"
        },
        {
          "character": "CHAKOTAY",
          "line": "An old Greek myth. After a dragon was killed in a war, its teeth were spread out over the battlefield. They took root and warriors sprung from the ground to continue the fighting. Captain's log, supplemental. We've revived nearly two hundred of the Vaadwaur and we're moving forward with our unexpected alliance."
        }
      ],
      "location": "Vaadwaur cave - central chamber"
    },
    {
      "dialogue": [
        {
          "character": "TUVOK",
          "line": "Voyager was pulled into the corridor two hundred light years from here."
        },
        {
          "character": "GAUL",
          "line": "Pulled in?"
        },
        {
          "character": "MORIN",
          "line": "There must have been a break along the radial wall."
        },
        {
          "character": "GEDRIN",
          "line": "The corridors occur naturally, but they're very unstable. They're damaged by use."
        },
        {
          "character": "GAUL",
          "line": "Obviously the Turei don't have the wisdom to maintain them properly. They'll be very difficult to navigate after centuries of neglect."
        },
        {
          "character": "TUVOK",
          "line": "We've only been able to chart a few of the corridors. Can you provide us with a more complete map?"
        },
        {
          "character": "MORIN",
          "line": "We've never kept written records, for security reasons. Of course, we've committed all the corridors to memory. Every multifold, every spatial intersect."
        },
        {
          "character": "GAUL",
          "line": "We'd be happy to plot a course for you but first, we'll need to get past the Turei, How many vessels are in orbit?"
        },
        {
          "character": "SEVEN",
          "line": "Eleven."
        },
        {
          "character": "JANEWAY",
          "line": "Mister Gaul, Tuvok, start working on a tactical plan."
        },
        {
          "character": "GEDRIN",
          "line": "If we do manage to escape, we'll need to locate a habitable world."
        },
        {
          "character": "JANEWAY",
          "line": "Seven, scan the Astrometric database. See what you can find. Someplace out of the way."
        },
        {
          "character": "GEDRIN",
          "line": "Morin, take charge of reviving the rest of our battalion."
        },
        {
          "character": "MORIN",
          "line": "Many of our bio-pods have been damaged. I could use some assistance."
        },
        {
          "character": "JANEWAY",
          "line": "Our Chief Engineer will be glad to give you a hand."
        },
        {
          "character": "MORIN",
          "line": "Thank you."
        },
        {
          "character": "JANEWAY",
          "line": "Well, let's get started. We've got a civilisation to rebuild."
        }
      ],
      "location": "Astrometrics lab"
    },
    {
      "dialogue": [
        {
          "character": "NEELIX",
          "line": "No story tonight, Naomi. I had to cook for two hundred people today."
        },
        {
          "character": "NAOMI",
          "line": "That's okay. I'm tired, too."
        },
        {
          "character": "NEELIX",
          "line": "Did you get a chance to meet any of the children?"
        },
        {
          "character": "NAOMI",
          "line": "I don't like them."
        },
        {
          "character": "NEELIX",
          "line": "Why not?"
        },
        {
          "character": "NAOMI",
          "line": "I just don't."
        },
        {
          "character": "NEELIX",
          "line": "Well, that's not good enough. I'm the ship's ambassador, you're the Captain's assistant. We have to make a good impression on our new friends."
        },
        {
          "character": "NAOMI",
          "line": "They're not my friends."
        },
        {
          "character": "NEELIX",
          "line": "Well, not yet. Listen. First thing tomorrow, you and I will get together with a couple of the children."
        },
        {
          "character": "NAOMI",
          "line": "No."
        },
        {
          "character": "NEELIX",
          "line": "Naomi, what's wrong?"
        },
        {
          "character": "NAOMI",
          "line": "Nothing. I don't like them and I don't want to play with them."
        },
        {
          "character": "NEELIX",
          "line": "That doesn't sound like you. Tell me what happened."
        },
        {
          "character": "NAOMI",
          "line": "They called you names."
        },
        {
          "character": "NEELIX",
          "line": "Names?"
        },
        {
          "character": "NAOMI",
          "line": "They said everybody from your planet was stupid. They said your ears were funny. They said just looking at you made them laugh. They said"
        },
        {
          "character": "NEELIX",
          "line": "I, I, I get the idea. Children can be a little cruel sometimes, but there's no need to take it personally. Besides, my ears are kind of funny."
        },
        {
          "character": "NAOMI",
          "line": "I don't want to play with them."
        },
        {
          "character": "NEELIX",
          "line": "No. And you don't have to."
        },
        {
          "character": "NAOMI",
          "line": "Okay."
        },
        {
          "character": "NEELIX",
          "line": "Come on."
        },
        {
          "character": "NEELIX",
          "line": "Goodnight. I'll tell you a story tomorrow, I promise."
        }
      ],
      "location": "Naomi's bedroom"
    },
    {
      "dialogue": [
        {
          "character": "TORRES",
          "line": "I'm not happy with these fluctuations. We may be trying to reactivate too many ships at once."
        },
        {
          "character": "MORIN",
          "line": "I suggest we focus on the assault fighters. Qual tel k'pok."
        },
        {
          "character": "TORRES",
          "line": "Thanks. When did you learn Klingon?"
        },
        {
          "character": "MORIN",
          "line": "Just a few phrases. I was studying your database. The Klingons are a noble race."
        },
        {
          "character": "TORRES",
          "line": "They have their moments."
        },
        {
          "character": "MORIN",
          "line": "Today is a good day to die."
        },
        {
          "character": "TORRES",
          "line": "Pardon?"
        },
        {
          "character": "MORIN",
          "line": "Kahless, your greatest warrior. That was his battle cry."
        },
        {
          "character": "TORRES",
          "line": "You seem to have taken an interest in Klingon history."
        },
        {
          "character": "MORIN",
          "line": "There are many parallels between our cultures. The Vaadwaur have also learned to embrace death without fear. As children, we're taught to fall asleep each night imagining a different way to die."
        },
        {
          "character": "TORRES",
          "line": "I prefer curling up with a good book."
        }
      ],
      "location": "Vaadwaur caves - central chamber"
    },
    {
      "dialogue": [
        {
          "character": "NEELIX",
          "line": "Computer, access my personal database."
        },
        {
          "character": "COMPUTER",
          "line": "Access established."
        },
        {
          "character": "NEELIX",
          "line": "Go into the Talaxian linguistic files, Old Tongue dialect. Find and define the word Vaadwaur."
        },
        {
          "character": "COMPUTER",
          "line": "Vaadwaur. Archaic adjective. Primary meaning, Foolish. Additional meanings, Weak-minded, reckless, blind."
        },
        {
          "character": "NEELIX",
          "line": "What's the first known usage?"
        },
        {
          "character": "COMPUTER",
          "line": "First written example appears in Eldaxon's Collected Folklore, second edition. Year of publication, 5012, new calendar."
        },
        {
          "character": "NEELIX",
          "line": "Computer, name the specific folktales that use the word vaadwaur."
        },
        {
          "character": "COMPUTER",
          "line": "The Demon with the Golden Voice. The Tale of the Deadly Stranger. The Tale of the Boy who Lost his Head. The Tale of the Bloody Hand."
        },
        {
          "character": "NEELIX",
          "line": "Not exactly Mother Goose. Computer, transfer the text of those stories to my quarters."
        },
        {
          "character": "COMPUTER",
          "line": "Transfer complete."
        }
      ],
      "location": "Mess hall"
    },
    {
      "dialogue": [
        {
          "character": "GEDRIN",
          "line": "That star cluster in grid fourteen twenty one? Nearly half the planets are inhabitable."
        },
        {
          "character": "SEVEN",
          "line": "Unfortunately they are already occupied. By the Borg."
        },
        {
          "character": "GEDRIN",
          "line": "The Borg? In my century they'd only assimilated a handful of systems. It looks like they've spread through the quadrant like a plague. No offense."
        },
        {
          "character": "SEVEN",
          "line": "None taken."
        },
        {
          "character": "GEDRIN",
          "line": "We had a colony near the twin star in grid three one five."
        },
        {
          "character": "SEVEN",
          "line": "That is part of the Devore Imperium now."
        },
        {
          "character": "GEDRIN",
          "line": "And who are they?"
        },
        {
          "character": "SEVEN",
          "line": "An authoritarian regime. They claim eleven systems across three sectors."
        },
        {
          "character": "GEDRIN",
          "line": "I don't suppose they'd be willing to negotiate for a continent or two."
        },
        {
          "character": "SEVEN",
          "line": "The Devore are intolerant of outsiders."
        },
        {
          "character": "GEDRIN",
          "line": "It doesn't matter. We have nothing to negotiate with. Our technology is nine hundred years out of date."
        },
        {
          "character": "SEVEN",
          "line": "Your pessimism is irrelevant. We will find a home for you."
        },
        {
          "character": "GEDRIN",
          "line": "I hope you're right."
        }
      ],
      "location": "Astrometrics lab"
    },
    {
      "dialogue": [
        {
          "character": "TUVOK",
          "line": "Sixteen Turei vessels are now in orbit. Long range sensors indicate five more on the way."
        },
        {
          "character": "JANEWAY",
          "line": "I can understand that they want the odds in their favor, but isn't that overkill?"
        },
        {
          "character": "GAUL",
          "line": "They may have detected us. If they know their history, they'll come prepared."
        },
        {
          "character": "JANEWAY",
          "line": "Nine hundred years is a long time to hold a grudge."
        },
        {
          "character": "GAUL",
          "line": "The Turei would like nothing more than to find the rest of our subspace corridors. We can't allow that to happen."
        },
        {
          "character": "TUVOK",
          "line": "Then I suggest we use the element of surprise. At oh six hundred, Voyager will leave the surface and engage the Turei ships in orbit. As we draw their fire, the more powerful Vaadwaur vessels will attack from multiple vectors. The rest of the Vaadwaur will break orbit from the opposite side of the planet and proceed to the subspace corridors. We'll rendezvous with them afterwards."
        },
        {
          "character": "GAUL",
          "line": "What if Voyager is disabled? We'll be defenseless. If we armed my ships with your photon torpedoes"
        },
        {
          "character": "JANEWAY",
          "line": "I can't authorize that."
        },
        {
          "character": "GAUL",
          "line": "Why?"
        },
        {
          "character": "JANEWAY",
          "line": "Starfleet protocols are very strict about the transfer of weapons."
        },
        {
          "character": "GAUL",
          "line": "I'm not used to putting my life in someone else's hands."
        },
        {
          "character": "JANEWAY",
          "line": "There are a lot of things you're going to have to get used to. We've faced enemies worse than the Turei. I'm confident we can handle them."
        },
        {
          "character": "GAUL",
          "line": "I need those weapons."
        },
        {
          "character": "JANEWAY",
          "line": "I'm sorry. The answer's no."
        },
        {
          "character": "GAUL",
          "line": "If you want access to our corridors."
        },
        {
          "character": "JANEWAY",
          "line": "We'll continue home through open space if we have to."
        },
        {
          "character": "GAUL",
          "line": "All right, our lives are in your hands."
        }
      ],
      "location": "Briefing room"
    },
    {
      "dialogue": [
        {
          "character": "GEDRIN",
          "line": "We found a planet in a nebula near the junction of corridors three nine and eight seven five. We'd be isolated and relatively safe."
        },
        {
          "character": "GAUL",
          "line": "Relatively?"
        },
        {
          "character": "GEDRIN",
          "line": "I'm afraid the planet is somewhat harsh. There are no large bodies of water and the vegetation is sparse."
        },
        {
          "character": "GAUL",
          "line": "This is absurd."
        },
        {
          "character": "CREWMAN",
          "line": "Ensign, we need a power coupling over here, on the double."
        },
        {
          "character": "GAUL",
          "line": "Our plan was to reoccupy one of our former colonies, gain allies, rebuild our forces, take back what was ours."
        },
        {
          "character": "GEDRIN",
          "line": "Our former colonies are destroyed or occupied by species that are far more advanced than we are."
        },
        {
          "character": "MORIN",
          "line": "Then we'll find a way to take them back."
        },
        {
          "character": "GEDRIN",
          "line": "With what, a battalion of obsolete ships and outdated weapons?"
        },
        {
          "character": "GAUL",
          "line": "No, with Voyager. I've been studying their technology, the control systems, propulsion, weaponry. We could learn to operate the vessel ourselves."
        },
        {
          "character": "GEDRIN",
          "line": "What are you saying?"
        },
        {
          "character": "GAUL",
          "line": "After they engage the Turei, they'll expect us to assist them. Instead, we'll attack. We'll put as many soldiers as we can onto Voyager and take it into the corridors."
        },
        {
          "character": "GEDRIN",
          "line": "This is a mistake. If we fail, we'll lose everything."
        },
        {
          "character": "GAUL",
          "line": "If you like, I can return you to your stasis pod. Inform the others."
        }
      ],
      "location": "Vaadwaur caves - central chamber"
    },
    {
      "dialogue": [
        {
          "character": "SEVEN",
          "line": "This is an M class planet in orbit of a type G star. We've located a subcontinent with edible vegetation and an underground water supply. Unfortunately, the region is subject to windstorms."
        },
        {
          "character": "GEDRIN",
          "line": "Not exactly paradise."
        },
        {
          "character": "SEVEN",
          "line": "You will adapt."
        },
        {
          "character": "GEDRIN",
          "line": "Practical and to the point, just like my wife. She had a knack for cutting to the truth."
        },
        {
          "character": "SEVEN",
          "line": "She must have been an efficient individual."
        },
        {
          "character": "GEDRIN",
          "line": "To say the least. You would have enjoyed her company. You are not at all like the Borg I knew."
        },
        {
          "character": "SEVEN",
          "line": "As a drone, I helped assimilate many civilisations. Now I have the opportunity to help reconstruct one. I find the experience gratifying."
        },
        {
          "character": "GEDRIN",
          "line": "So do I. I'm curious. Has your crew ever considered finding a planet of their own? A place to settle down?"
        },
        {
          "character": "SEVEN",
          "line": "Captain Janeway is committed to getting Voyager back to Earth."
        },
        {
          "character": "GEDRIN",
          "line": "That could take decades, and there are many dangers ahead."
        },
        {
          "character": "SEVEN",
          "line": "We will adapt."
        },
        {
          "character": "GEDRIN",
          "line": "I suppose you will."
        },
        {
          "character": "NEELIX",
          "line": "Neelix to Seven of Nine.",
          "modifier": "voiceover"
        },
        {
          "character": "SEVEN",
          "line": "Yes?"
        },
        {
          "character": "NEELIX",
          "line": "Could I see you in Cargo Bay two? It's important.",
          "modifier": "voiceover"
        },
        {
          "character": "SEVEN",
          "line": "Acknowledged."
        },
        {
          "character": "GEDRIN",
          "line": "I'm due for a final briefing with your Mister Tuvok."
        },
        {
          "character": "SEVEN",
          "line": "I'll accompany you to the bridge."
        }
      ],
      "location": "Astrometrics lab"
    },
    {
      "dialogue": [
        {
          "character": "NEELIX",
          "line": "I'm sorry to bother you, but I've been doing some research on our new allies and I have found something very interesting. In dozens of the ancient folktales of my people, there's a common theme. They describe a phantom army that appears out of thin air, destroys entire colonies, and vanishes in the blink of an eye. Sound familiar?"
        },
        {
          "character": "SEVEN",
          "line": "The subspace corridors."
        },
        {
          "character": "NEELIX",
          "line": "Exactly. Gedrin claims they've been using them as trade routes but I'm starting to wonder."
        },
        {
          "character": "SEVEN",
          "line": "Your source material is folktales, Mister Neelix."
        },
        {
          "character": "NEELIX",
          "line": "But many fables have a basis in reality. You've got the collective knowledge of thousands of species. You could cross-reference my findings. It'll only take a few minutes."
        }
      ],
      "location": "Cargo Bay two"
    },
    {
      "dialogue": [
        {
          "character": "JANEWAY",
          "line": "Come in."
        },
        {
          "character": "GEDRIN",
          "line": "You wanted to see me, Captain?"
        },
        {
          "character": "JANEWAY",
          "line": "Yes. I need a little history lesson."
        },
        {
          "character": "GEDRIN",
          "line": "Can't it wait until after we've reached the corridors?"
        },
        {
          "character": "JANEWAY",
          "line": "I'm afraid not. I've just had a conversation with Mister Neelix and Seven of Nine. They've been poring through various databases and ha've come up with some surprising findings."
        },
        {
          "character": "GEDRIN",
          "line": "Surprising?"
        },
        {
          "character": "JANEWAY",
          "line": "You told me the Vaadwaur were a culture of merchants and scientists who expanded their knowledge by using subspace corridors to travel to other worlds. You were the envy of hundreds of species, some of whom eventually wanted the corridors for themselves."
        },
        {
          "character": "GEDRIN",
          "line": "Your point?"
        },
        {
          "character": "JANEWAY",
          "line": "Let me give you another version of events. The Vaadwaur were an aggressive culture who expanded their territory by using the corridors to attack other worlds, until some of those worlds banded together to defend themselves and put an end to the Vaadwaur threat once and for all. Would you care to set the record straight?"
        },
        {
          "character": "GEDRIN",
          "line": "That was nine hundred years ago."
        },
        {
          "character": "JANEWAY",
          "line": "If we're going to be fighting side by side, I have to trust you. I need to be certain you don't have any ulterior motives."
        },
        {
          "character": "GEDRIN",
          "line": "Our only motive is survival."
        },
        {
          "character": "JANEWAY",
          "line": "If I were to take you at your word, the ancient Talaxians might call me vaadwaur. Foolish. That's what they came to call anyone who allowed themselves to be deceived by an enemy. There are hundreds of other references just like it."
        },
        {
          "character": "GEDRIN",
          "line": "Both versions of our history are true. We did use the corridors to explore and, on occasion, expand our territory. But Captain, we have gone from a population of six billion to six hundred. Our weapons are archaic. Do you really think that we are prepared to declare war on the Delta Quadrant?"
        },
        {
          "character": "JANEWAY",
          "line": "Not yet, but right now it's Voyager I'm worried about. The Turei are going to be firing everything they've got at my ship. You might try to take advantage of that."
        },
        {
          "character": "GEDRIN",
          "line": "What are you going to do, put us all back into stasis?"
        },
        {
          "character": "JANEWAY",
          "line": "We said we'd try to help you make a new start, and I want to keep that promise. But I can't ignore history, Mister Gedrin."
        }
      ],
      "location": "Ready room"
    },
    {
      "dialogue": [
        {
          "character": "JANEWAY",
          "line": "Make yourself comfortable, Mister Gedrin. Chakotay, I don't know whether to believe him or not. What I wouldn't give for a Betazoid about now."
        },
        {
          "character": "CHAKOTAY",
          "line": "If Mister Neelix is right, we should be ready for anything. Their technology may be outdated, but it can still do a lot of damage."
        },
        {
          "character": "JANEWAY",
          "line": "Agreed. Maintain a full security alert and have Tuvok keep a weapons lock on their primary reactor."
        },
        {
          "character": "CHAKOTAY",
          "line": "Are we still proceeding at oh six hundred hours?"
        },
        {
          "character": "JANEWAY",
          "line": "Yes, but with a few modifications. What's Mister Gaul's location?"
        },
        {
          "character": "KIM",
          "line": "He's in the central chamber."
        },
        {
          "character": "JANEWAY",
          "line": "Hail him."
        },
        {
          "character": "GAUL",
          "line": "Captain, we've reactivated seventy three assault vessels. Our pilots are standing by.",
          "modifier": "screen"
        },
        {
          "character": "JANEWAY",
          "line": "I need to inform you about a change of plan. I want you to deactivate the particle cannons on all but ten of your assault vessels. Then we'll proceed on schedule."
        },
        {
          "character": "GAUL",
          "line": "I don't understand.",
          "modifier": "screen"
        },
        {
          "character": "JANEWAY",
          "line": "Only ten of your ships are going to engage the Turei. The others will head directly for the subspace corridors. I see no reason for those to be armed."
        },
        {
          "character": "GAUL",
          "line": "Something could go wrong. Why leave them defenseless?",
          "modifier": "screen"
        },
        {
          "character": "JANEWAY",
          "line": "Voyager will defend them."
        },
        {
          "character": "GAUL",
          "line": "What prompted this change?",
          "modifier": "screen"
        },
        {
          "character": "JANEWAY",
          "line": "You haven't been completely honest about your past, and that makes me a little uncertain about the present."
        },
        {
          "character": "GAUL",
          "line": "Gedrin.",
          "modifier": "screen"
        },
        {
          "character": "GEDRIN",
          "line": "I suggest you listen to her."
        },
        {
          "character": "GAUL",
          "line": "Request denied, Captain.",
          "modifier": "screen"
        },
        {
          "character": "JANEWAY",
          "line": "It's not a request. You can call it an ultimatum if you like."
        },
        {
          "character": "GAUL",
          "line": "Unacceptable.",
          "modifier": "screen"
        },
        {
          "character": "JANEWAY",
          "line": "I'm going to leave this planet in one hour, with or without you."
        },
        {
          "character": "GAUL",
          "line": "We did not spend nine hundred years in stasis to take orders from you.",
          "modifier": "screen"
        }
      ],
      "location": "Bridge"
    },
    {
      "dialogue": [
        {
          "character": "GAUL",
          "line": "Contact the battalion. Tell them to prepare for the attack."
        }
      ],
      "location": "Vaadwaur cave - central chamber"
    },
    {
      "dialogue": [
        {
          "character": "JANEWAY",
          "line": "I don't know about the rest of you but I'm ready to get moving. What's our status?"
        },
        {
          "character": "PARIS",
          "line": "Impulse engines are online."
        },
        {
          "character": "TUVOK",
          "line": "Shields at maximum. Weapons standing by."
        },
        {
          "character": "JANEWAY",
          "line": "Tom, prepare to initiate the ascent sequence in"
        },
        {
          "character": "CHAKOTAY",
          "line": "Report!"
        },
        {
          "character": "KIM",
          "line": "Massive energy readings coming from the central chamber."
        },
        {
          "character": "TUVOK",
          "line": "It's the Vaadwaur. They're launching the first wave of ships. Seventeen vessels have broken through the surface. They're at an altitude of two thousand meters and charging weapons."
        },
        {
          "character": "PARIS",
          "line": "Ma'am, they're not ascending into orbit. They're heading straight for Voyager."
        },
        {
          "character": "JANEWAY",
          "line": "Tom?"
        },
        {
          "character": "PARIS",
          "line": "Engaging thrusters. Initiating ascent sequence."
        },
        {
          "character": "TUVOK",
          "line": "Vaadwaur ships approaching off our starboard bow."
        },
        {
          "character": "JANEWAY",
          "line": "Target phasers, full spread."
        },
        {
          "character": "PARIS",
          "line": "We're airborne."
        },
        {
          "character": "CHAKOTAY",
          "line": "What altitude do we need on this planet, Tom, before we can go to warp?"
        },
        {
          "character": "PARIS",
          "line": "We'll have to clear the thermosphere. Two hundred and eighty kilometers at least."
        },
        {
          "character": "TUVOK",
          "line": "Shields at ninety two percent."
        },
        {
          "character": "JANEWAY",
          "line": "Phasers."
        },
        {
          "character": "TUVOK",
          "line": "We've disabled four of their ships."
        },
        {
          "character": "CHAKOTAY",
          "line": "They've launched another thirty nine vessels."
        },
        {
          "character": "JANEWAY",
          "line": "Evasive maneuvers."
        },
        {
          "character": "PARIS",
          "line": "It's no use. They're closing on all sides."
        },
        {
          "character": "KIM",
          "line": "Direct hit to the port thrusters."
        },
        {
          "character": "PARIS",
          "line": "We're losing altitude."
        },
        {
          "character": "JANEWAY",
          "line": "Reroute emergency power. We need to get into orbit."
        },
        {
          "character": "TUVOK",
          "line": "Targeting sensors offline. Switching to manual."
        },
        {
          "character": "JANEWAY",
          "line": "Harry, can you open a secure channel to the Turei ships in orbit?"
        },
        {
          "character": "KIM",
          "line": "Yes, ma'am, but that would give away our position. They could lock on with plasma charges."
        },
        {
          "character": "JANEWAY",
          "line": "I think it's time we reacquaint a couple of old friends. Hail them."
        }
      ],
      "location": "Bridge"
    },
    {
      "dialogue": [
        {
          "character": "MORIN",
          "line": "Voyager's shields are weakening but they're gaining altitude again. They're approaching the thermosphere."
        },
        {
          "character": "GAUL",
          "line": "Launch another squadron."
        }
      ],
      "location": "Vaadwaur caves - central chamber"
    },
    {
      "dialogue": [
        {
          "character": "PARIS",
          "line": "We've got nine more fighters on our tail."
        },
        {
          "character": "TUVOK",
          "line": "Aft shields down to twenty percent."
        },
        {
          "character": "KIM",
          "line": "Captain, the Turei are responding."
        },
        {
          "character": "JANEWAY",
          "line": "Put them through."
        },
        {
          "character": "TUREI",
          "line": "What do you want?",
          "modifier": "screen"
        },
        {
          "character": "JANEWAY",
          "line": "I've got a proposition for you."
        },
        {
          "character": "TUREI",
          "line": "No more talk. Prepare to be bordered.",
          "modifier": "screen"
        },
        {
          "character": "JANEWAY",
          "line": "Tell me, have you been picking up weapons fire?"
        },
        {
          "character": "TUREI",
          "line": "We have detected some unusual energy signatures, yes.",
          "modifier": "screen"
        },
        {
          "character": "JANEWAY",
          "line": "That's because we're under attack by the Vaadwaur."
        },
        {
          "character": "TUREI",
          "line": "Impossible. They were destroyed centuries ago.",
          "modifier": "screen"
        },
        {
          "character": "GEDRIN",
          "line": "Some of us have survived."
        },
        {
          "character": "JANEWAY",
          "line": "They've got over two hundred ships. They said something about wanting their subspace corridors back. I suggest we join forces and try to neutralize the threat here and now. What's more important to you? Deleting the records of a Federation ship that means you no harm, or defending yourselves against hundreds of Vaadwaur fighters who are determined to invade your underspace? I suggest you pick your enemy."
        },
        {
          "character": "TUREI",
          "line": "Our sensors can't penetrate the atmosphere. How can we fight an enemy we can't see?"
        },
        {
          "character": "CHAKOTAY",
          "line": "We have access to one of their surveillance satellites. We could use it to transmit their vital coordinates to you."
        },
        {
          "character": "TUREI",
          "line": "If this is a deception",
          "modifier": "screen"
        },
        {
          "character": "KIM",
          "line": "I'm having trouble establishing a link with the satellite. Our sensor array took heavy damage."
        },
        {
          "character": "GEDRIN",
          "line": "I could access it from the underground control chamber. Transport me there. Not all of my people are stuck in the past, Captain."
        },
        {
          "character": "JANEWAY",
          "line": "Tuvok, go with him."
        }
      ],
      "location": "Bridge"
    },
    {
      "dialogue": [
        {
          "character": "MORIN",
          "line": "We've impacted their hull. There are breaches in progress on two decks."
        },
        {
          "character": "GAUL",
          "line": "They'll have to reroute power from their shields to seal them. They'll have no choice but to put down. Have our ground forces ready."
        }
      ],
      "location": "Vaadwaur caves - central chamber"
    },
    {
      "dialogue": [
        {
          "character": "KIM",
          "line": "We've lost impulse engines and navigation."
        },
        {
          "character": "PARIS",
          "line": "Thrusters are failing. We're losing altitude."
        },
        {
          "character": "JANEWAY",
          "line": "Tuvok, status. Tuvok?"
        },
        {
          "character": "KIM",
          "line": "I've lost the signal."
        },
        {
          "character": "JANEWAY",
          "line": "All hands, this is the Captain. Initiate emergency landing procedures, and arm yourselves. If the Vaadwaur board this ship, we'll fight them hand to hand if we have to."
        }
      ],
      "location": "Bridge"
    },
    {
      "dialogue": [
        {
          "character": "MORIN",
          "line": "Once we've secured Voyager, execute the crew."
        },
        {
          "character": "GAUL",
          "line": "Wait. We have hundreds of bio-pods still intact. Put them into stasis. In a few hundred years, maybe someone will be kind enough to revive them."
        },
        {
          "character": "GAUL",
          "line": "What is that?"
        },
        {
          "character": "MORIN",
          "line": "It's a plasma charge. It came from orbit. It's the Turei. They've isolated our location."
        },
        {
          "character": "GAUL",
          "line": "How?"
        },
        {
          "character": "MORIN",
          "line": "One of the surveillances satellite has been activated."
        },
        {
          "character": "GAUL",
          "line": "Shut it down."
        }
      ],
      "location": "Vaadwaur caves - central chamber"
    },
    {
      "dialogue": [
        {
          "character": "GEDRIN",
          "line": "They're blocking my commands. I'm rotating the carrier frequencies."
        },
        {
          "character": "TUVOK",
          "line": "The chamber is destabilizing. We must evacuate."
        },
        {
          "character": "GEDRIN",
          "line": "Not yet. If we're going to succeed, I need to transmit the signatures of our fighters to the Turei. You go."
        }
      ],
      "location": "Vaadwaur caves - control chamber"
    },
    {
      "dialogue": [
        {
          "character": "CHAKOTAY",
          "line": "Six Vaadwaur ships were just destroyed by the Turei. The others are breaking off their attack."
        },
        {
          "character": "JANEWAY",
          "line": "Impulse engines?"
        },
        {
          "character": "PARIS",
          "line": "Still offline."
        },
        {
          "character": "JANEWAY",
          "line": "How about emergency power?"
        },
        {
          "character": "KIM",
          "line": "Barely enough for life support, Captain."
        },
        {
          "character": "JANEWAY",
          "line": "Harry, the radiogenic particles in the atmosphere. Could we use them as a power source?"
        },
        {
          "character": "KIM",
          "line": "We'd have to modify the warp core's conversion matrix. It could take hours."
        },
        {
          "character": "JANEWAY",
          "line": "What if we drew the particles directly into our plasma manifold?"
        },
        {
          "character": "PARIS",
          "line": "That would give us one hell of a boost."
        },
        {
          "character": "KIM",
          "line": "It could also blow out every power relay on the ship."
        },
        {
          "character": "JANEWAY",
          "line": "Damned if we do, damned if we don't. Open the forward nacelle ports and reverse the pressure gradient. Take in six hundred kilograms."
        }
      ],
      "location": "Bridge"
    },
    {
      "dialogue": [
        {
          "character": "VAADWAUR",
          "line": "The chamber's collapsing, sir."
        },
        {
          "character": "GAUL",
          "line": "We'll take as many ships as we can. Try to reach the subspace corridor."
        }
      ],
      "location": "Vaadwaur caves - central chamber"
    },
    {
      "dialogue": [
        {
          "character": "KIM",
          "line": "Particle concentration at three thousand parts per million."
        },
        {
          "character": "JANEWAY",
          "line": "Release the manifold."
        },
        {
          "character": "PARIS",
          "line": "Rerouting plasma to the power conduits. We have impulse."
        },
        {
          "character": "JANEWAY",
          "line": "Take us up."
        },
        {
          "character": "KIM",
          "line": "Thirteen power relays just blew out on deck six."
        },
        {
          "character": "JANEWAY",
          "line": "Steady."
        },
        {
          "character": "PARIS",
          "line": "We're crossing the thermosphere."
        },
        {
          "character": "JANEWAY",
          "line": "Any sign of pursuit?"
        },
        {
          "character": "CHAKOTAY",
          "line": "None. Looks like the Vaadwaur have their hands full."
        },
        {
          "character": "JANEWAY",
          "line": "Altitude?"
        },
        {
          "character": "PARIS",
          "line": "Two hundred and sixty kilometers, two hundred and seventy. We've cleared the thermosphere."
        },
        {
          "character": "JANEWAY",
          "line": "Go to warp, Mister Paris."
        },
        {
          "character": "PARIS",
          "line": "Yes, ma'am. Captain's log, stardate 53167.9. After two days, there's been no sign of the Vaadwaur or the Turei. However, Seven of Nine has made an unsettling discovery."
        }
      ],
      "location": "Bridge"
    },
    {
      "dialogue": [
        {
          "character": "JANEWAY",
          "line": "How many ships?"
        },
        {
          "character": "SEVEN",
          "line": "Astrometrics scans detected fifty three ion signatures entering the corridors. All Vaadwaur."
        },
        {
          "character": "JANEWAY",
          "line": "The underground chambers?"
        },
        {
          "character": "SEVEN",
          "line": "They were destroyed by the Turei bombardment. Captain, I believe I made an error in judgment."
        },
        {
          "character": "JANEWAY",
          "line": "Oh?"
        },
        {
          "character": "SEVEN",
          "line": "By awakening Gedrin, I initiated a chain of events that nearly led to our destruction. I wanted to help revive a civilisation, not start a war."
        },
        {
          "character": "JANEWAY",
          "line": "You thought you were acting out of compassion. I might have done the same thing. But that doesn't make it right, Seven. The repercussions of this could be catastrophic."
        },
        {
          "character": "SEVEN",
          "line": "Their technology is nine centuries out of date. Their plans for conquest are irrelevant."
        },
        {
          "character": "JANEWAY",
          "line": "They're a resourceful species, determined. They'll adapt. I doubt we've seen the last of them."
        }
      ],
      "location": "Ready room"
    }
  ],
  "schedule": {
    "episode": 7,
    "number": 127,
    "season": 6
  },
  "stardate": "53167.9",
  "title": "Dragon's Teeth"
}